MANIFEST.in
README.rst
setup.py
tox.ini
tests/__init__.py
tests/__init__.pyc
tests/conftest.py
tests/conftest.pyc
tests/test_pagination.py
tests/test_schema_args.py
tests/test_sorting.py
tests/test_strict_json.py
tests/test_weber_utils.py
weber_utils/__init__.py
weber_utils/__version__.py
weber_utils/_compat.py
weber_utils/pagination.py
weber_utils/request_utils.py
weber_utils/sorting.py
weber_utils/strict.py
weber_utils.egg-info/PKG-INFO
weber_utils.egg-info/SOURCES.txt
weber_utils.egg-info/dependency_links.txt
weber_utils.egg-info/namespace_packages.txt
weber_utils.egg-info/requires.txt
weber_utils.egg-info/top_level.txt