Metadata-Version: 1.1
Name: weber-utils
Version: 1.2.1
Summary: Utilities for the Weber flask template
Home-page: https://github.com/vmalloc/weber-utils
Author: Rotem Yaari
Author-email: vmalloc@gmail.com
License: BSD3
Platform: UNKNOWN
Classifier: Programming Language :: Python :: 2.6
Classifier: Programming Language :: Python :: 2.7
Classifier: Programming Language :: Python :: 3.3
